README.rst
setup.cfg
setup.py
src/pyneric/__init__.py
src/pyneric/_version.py
src/pyneric/fsnotify.py
src/pyneric/meta.py
src/pyneric/requests.py
src/pyneric/rest_requests.py
src/pyneric/util.py
src/pyneric.egg-info/PKG-INFO
src/pyneric.egg-info/SOURCES.txt
src/pyneric.egg-info/dependency_links.txt
src/pyneric.egg-info/pbr.json
src/pyneric.egg-info/requires.txt
src/pyneric.egg-info/top_level.txt
src/pyneric/django/__init__.py
src/pyneric/django/db/__init__.py
src/pyneric/django/db/models/__init__.py
src/pyneric/django/db/models/fields/__init__.py
src/pyneric/django/db/models/fields/pguuid.py
src/pyneric/future/__init__.py
src/pyneric/future/newstr.py
src/pyneric/future/newsuper.py
src/pyneric/future/newtype.py
src/pyneric/http/__init__.py
src/pyneric/http/v1_1/__init__.py
src/pyneric/http/v1_1/core.py
src/pyneric/http/v1_1/patch.py